LICENSE
README.rst
setup.cfg
setup.py
cgnlib/__init__.py
cgnlib/cgnexp.py
cgnlib/cgnlib.py
cgnlib/conf.py
cgnlib.egg-info/PKG-INFO
cgnlib.egg-info/SOURCES.txt
cgnlib.egg-info/dependency_links.txt
cgnlib.egg-info/requires.txt
cgnlib.egg-info/top_level.txt