Metadata-Version: 2.1
Name: cgnlib
Version: 0.1.6
Summary: CGNLib, a Python library, enhances GN by allowing experimentation with different centrality metric. This flexibility can improve community detection results.
Home-page: https://github.com/chinnapongpsu/cgnlib
Download-URL: https://github.com/chinnapongpsu/cgnlib/archive/refs/tags/0.1.6.zip
Author: chinnapongpsu
Author-email: chinnapong.a@psu.ac.th
License: MIT
Keywords: cgn,Community DetectionCommunity,DetectionGirvan-NewmanCentrality Metrics
Classifier: Development Status :: 3 - Alpha
Classifier: Intended Audience :: Education
Classifier: Topic :: Utilities
Classifier: License :: OSI Approved :: MIT License
Classifier: Programming Language :: Python :: 3
Classifier: Programming Language :: Python :: 3.4
Classifier: Programming Language :: Python :: 3.5
Classifier: Programming Language :: Python :: 3.6
Classifier: Programming Language :: Python :: 3.7
Classifier: Programming Language :: Python :: 3.8
Classifier: Programming Language :: Python :: 3.9
Classifier: Programming Language :: Python :: 3.10
License-File: LICENSE
Requires-Dist: networkx
Requires-Dist: igraph
Requires-Dist: netcenlib
Requires-Dist: matplotlib
